README.rst
setup.py
pykevocontrol.egg-info/PKG-INFO
pykevocontrol.egg-info/SOURCES.txt
pykevocontrol.egg-info/dependency_links.txt
pykevocontrol.egg-info/requires.txt
pykevocontrol.egg-info/top_level.txt
pykevoplus/__init__.py