Metadata-Version: 1.0
Name: pykevocontrol
Version: 2.0.0
Summary: Control Kwikset Kevo locks
Home-page: https://github.com/bahnburner/pykevoplus
Author: Tristan Caulfield
Author-email: tcaulfld@gmail.com
License: MIT
Keywords: kevo kwikset
Platform: UNKNOWN
